shapex/__init__.py
shapex/alphabet/__init__.py
shapex/alphabet/const_letter.py
shapex/alphabet/exp_letter.py
shapex/alphabet/letter.py
shapex/alphabet/letter_type.py
shapex/alphabet/line_letter.py
shapex/alphabet/sinc_letter.py
shapex/alphabet/sine_letter.py
shapex/expression/Expression.py
shapex/expression/ExpressionVisitor.py
shapex/expression/__init__.py
shapex/generation_tool/__init__.py
shapex/generation_tool/generate_traces.py
shapex/generation_tool/ideal_atomics.py
shapex/misc/Error.py
shapex/misc/Warnings.py
shapex/misc/__init__.py
shapex/misc/save.py
shapex/misc/visualize.py
shapex/parse/SyntaxError.py
shapex/parse/__init__.py
shapex/parse/expression2aut/__init__.py
shapex/parse/expression2aut/expression2aut.py
shapex/parse/expression2aut/automaton/__init__.py
shapex/parse/expression2aut/automaton/automaton.py
shapex/parse/expression2aut/automaton/interval.py
shapex/parse/expression2aut/automaton/location.py
shapex/parse/expression2aut/automaton/transition.py
shapex/parse/generated/ShapeExpressionLexer.py
shapex/parse/generated/ShapeExpressionParser.py
shapex/parse/generated/ShapeExpressionVisitor.py
shapex/parse/generated/__init__.py
shapex/shapex/ShapEx.py
shapex/shapex/SpecLoaderVisitor.py
shapex/shapex/__init__.py
shapex/tests/__init__.py
shapex/tests/det.py
shapex/tests/template.py
shapex/tests/test_runner.py
shapex/tests/tmp_test.py
shapex/word_sampler/__init__.py
shapex/word_sampler/sapathfinder/__init__.py
shapex/word_sampler/sapathfinder/find_paths.py
shapex/word_sampler/visitors/BoltzmannSampler.py
shapex/word_sampler/visitors/RE2SAVisitor.py
shapex/word_sampler/visitors/__init__.py
ShapEx-1.0.0.dist-info/LICENSE
ShapEx-1.0.0.dist-info/METADATA
ShapEx-1.0.0.dist-info/WHEEL
ShapEx-1.0.0.dist-info/top_level.txt
ShapEx-1.0.0.dist-info/RECORD
