Metadata-Version: 2.1
Name: ShapEx
Version: 1.0.0
Summary: Library for sampling shape expressions.
Home-page: https://github.com/figlerg/ShapEx.git
Author: Felix Gigler, Dejan Nickovic, Mateis Cristinel, Nicolas Basset, Thao Dang
Author-email: felix.gigler.fl@ait.ac.at
License: BSD
Platform: UNKNOWN
Classifier: License :: OSI Approved :: BSD License
Classifier: Programming Language :: Python :: 3
Classifier: Operating System :: OS Independent
Requires-Python: >=3.5
License-File: LICENSE
Requires-Dist: tqdm
Requires-Dist: matplotlib
Requires-Dist: numpy
Requires-Dist: z3-solver
Requires-Dist: antlr4-python3-runtime
Requires-Dist: anyHR
